[
  {
    "method": "TurboQuant 2-bit",
    "bit_width": 2,
    "k": 1,
    "recall_1_at_k": 0.342,
    "quant_time_s": 0.00873708724975586,
    "search_time_s": 0.2693824768066406,
    "bytes_per_vec": 54
  },
  {
    "method": "TurboQuant 2-bit",
    "bit_width": 2,
    "k": 2,
    "recall_1_at_k": 0.497,
    "quant_time_s": 0.00873708724975586,
    "search_time_s": 0.2693824768066406,
    "bytes_per_vec": 54
  },
  {
    "method": "TurboQuant 2-bit",
    "bit_width": 2,
    "k": 4,
    "recall_1_at_k": 0.639,
    "quant_time_s": 0.00873708724975586,
    "search_time_s": 0.2693824768066406,
    "bytes_per_vec": 54
  },
  {
    "method": "TurboQuant 2-bit",
    "bit_width": 2,
    "k": 8,
    "recall_1_at_k": 0.77,
    "quant_time_s": 0.00873708724975586,
    "search_time_s": 0.2693824768066406,
    "bytes_per_vec": 54
  },
  {
    "method": "TurboQuant 2-bit",
    "bit_width": 2,
    "k": 16,
    "recall_1_at_k": 0.887,
    "quant_time_s": 0.00873708724975586,
    "search_time_s": 0.2693824768066406,
    "bytes_per_vec": 54
  },
  {
    "method": "TurboQuant 2-bit",
    "bit_width": 2,
    "k": 32,
    "recall_1_at_k": 0.951,
    "quant_time_s": 0.00873708724975586,
    "search_time_s": 0.2693824768066406,
    "bytes_per_vec": 54
  },
  {
    "method": "TurboQuant 2-bit",
    "bit_width": 2,
    "k": 64,
    "recall_1_at_k": 0.983,
    "quant_time_s": 0.00873708724975586,
    "search_time_s": 0.2693824768066406,
    "bytes_per_vec": 54
  },
  {
    "method": "TurboQuant 3-bit",
    "bit_width": 3,
    "k": 1,
    "recall_1_at_k": 0.577,
    "quant_time_s": 0.0001201629638671875,
    "search_time_s": 0.16369199752807617,
    "bytes_per_vec": 79
  },
  {
    "method": "TurboQuant 3-bit",
    "bit_width": 3,
    "k": 2,
    "recall_1_at_k": 0.768,
    "quant_time_s": 0.0001201629638671875,
    "search_time_s": 0.16369199752807617,
    "bytes_per_vec": 79
  },
  {
    "method": "TurboQuant 3-bit",
    "bit_width": 3,
    "k": 4,
    "recall_1_at_k": 0.902,
    "quant_time_s": 0.0001201629638671875,
    "search_time_s": 0.16369199752807617,
    "bytes_per_vec": 79
  },
  {
    "method": "TurboQuant 3-bit",
    "bit_width": 3,
    "k": 8,
    "recall_1_at_k": 0.963,
    "quant_time_s": 0.0001201629638671875,
    "search_time_s": 0.16369199752807617,
    "bytes_per_vec": 79
  },
  {
    "method": "TurboQuant 3-bit",
    "bit_width": 3,
    "k": 16,
    "recall_1_at_k": 0.993,
    "quant_time_s": 0.0001201629638671875,
    "search_time_s": 0.16369199752807617,
    "bytes_per_vec": 79
  },
  {
    "method": "TurboQuant 3-bit",
    "bit_width": 3,
    "k": 32,
    "recall_1_at_k": 0.998,
    "quant_time_s": 0.0001201629638671875,
    "search_time_s": 0.16369199752807617,
    "bytes_per_vec": 79
  },
  {
    "method": "TurboQuant 3-bit",
    "bit_width": 3,
    "k": 64,
    "recall_1_at_k": 0.999,
    "quant_time_s": 0.0001201629638671875,
    "search_time_s": 0.16369199752807617,
    "bytes_per_vec": 79
  },
  {
    "method": "TurboQuant 4-bit",
    "bit_width": 4,
    "k": 1,
    "recall_1_at_k": 0.78,
    "quant_time_s": 0.00024271011352539062,
    "search_time_s": 1.1595358848571777,
    "bytes_per_vec": 104
  },
  {
    "method": "TurboQuant 4-bit",
    "bit_width": 4,
    "k": 2,
    "recall_1_at_k": 0.915,
    "quant_time_s": 0.00024271011352539062,
    "search_time_s": 1.1595358848571777,
    "bytes_per_vec": 104
  },
  {
    "method": "TurboQuant 4-bit",
    "bit_width": 4,
    "k": 4,
    "recall_1_at_k": 0.977,
    "quant_time_s": 0.00024271011352539062,
    "search_time_s": 1.1595358848571777,
    "bytes_per_vec": 104
  },
  {
    "method": "TurboQuant 4-bit",
    "bit_width": 4,
    "k": 8,
    "recall_1_at_k": 0.999,
    "quant_time_s": 0.00024271011352539062,
    "search_time_s": 1.1595358848571777,
    "bytes_per_vec": 104
  },
  {
    "method": "TurboQuant 4-bit",
    "bit_width": 4,
    "k": 16,
    "recall_1_at_k": 1.0,
    "quant_time_s": 0.00024271011352539062,
    "search_time_s": 1.1595358848571777,
    "bytes_per_vec": 104
  },
  {
    "method": "TurboQuant 4-bit",
    "bit_width": 4,
    "k": 32,
    "recall_1_at_k": 1.0,
    "quant_time_s": 0.00024271011352539062,
    "search_time_s": 1.1595358848571777,
    "bytes_per_vec": 104
  },
  {
    "method": "TurboQuant 4-bit",
    "bit_width": 4,
    "k": 64,
    "recall_1_at_k": 1.0,
    "quant_time_s": 0.00024271011352539062,
    "search_time_s": 1.1595358848571777,
    "bytes_per_vec": 104
  },
  {
    "method": "FAISS FlatIP",
    "k": 1,
    "recall_1_at_k": 1.0,
    "build_time_s": 0.052826881408691406,
    "search_time_s": 1.2677891254425049,
    "bytes_per_vec": 800
  },
  {
    "method": "FAISS FlatIP",
    "k": 2,
    "recall_1_at_k": 1.0,
    "build_time_s": 0.052826881408691406,
    "search_time_s": 1.2677891254425049,
    "bytes_per_vec": 800
  },
  {
    "method": "FAISS FlatIP",
    "k": 4,
    "recall_1_at_k": 1.0,
    "build_time_s": 0.052826881408691406,
    "search_time_s": 1.2677891254425049,
    "bytes_per_vec": 800
  },
  {
    "method": "FAISS FlatIP",
    "k": 8,
    "recall_1_at_k": 1.0,
    "build_time_s": 0.052826881408691406,
    "search_time_s": 1.2677891254425049,
    "bytes_per_vec": 800
  },
  {
    "method": "FAISS FlatIP",
    "k": 16,
    "recall_1_at_k": 1.0,
    "build_time_s": 0.052826881408691406,
    "search_time_s": 1.2677891254425049,
    "bytes_per_vec": 800
  },
  {
    "method": "FAISS FlatIP",
    "k": 32,
    "recall_1_at_k": 1.0,
    "build_time_s": 0.052826881408691406,
    "search_time_s": 1.2677891254425049,
    "bytes_per_vec": 800
  },
  {
    "method": "FAISS FlatIP",
    "k": 64,
    "recall_1_at_k": 1.0,
    "build_time_s": 0.052826881408691406,
    "search_time_s": 1.2677891254425049,
    "bytes_per_vec": 800
  },
  {
    "method": "FAISS PQ m=8",
    "k": 1,
    "recall_1_at_k": 0.003,
    "build_time_s": 14.31606125831604,
    "search_time_s": 0.018481969833374023,
    "bytes_per_vec": 12
  },
  {
    "method": "FAISS PQ m=8",
    "k": 2,
    "recall_1_at_k": 0.007,
    "build_time_s": 14.31606125831604,
    "search_time_s": 0.018481969833374023,
    "bytes_per_vec": 12
  },
  {
    "method": "FAISS PQ m=8",
    "k": 4,
    "recall_1_at_k": 0.014,
    "build_time_s": 14.31606125831604,
    "search_time_s": 0.018481969833374023,
    "bytes_per_vec": 12
  },
  {
    "method": "FAISS PQ m=8",
    "k": 8,
    "recall_1_at_k": 0.021,
    "build_time_s": 14.31606125831604,
    "search_time_s": 0.018481969833374023,
    "bytes_per_vec": 12
  },
  {
    "method": "FAISS PQ m=8",
    "k": 16,
    "recall_1_at_k": 0.034,
    "build_time_s": 14.31606125831604,
    "search_time_s": 0.018481969833374023,
    "bytes_per_vec": 12
  },
  {
    "method": "FAISS PQ m=8",
    "k": 32,
    "recall_1_at_k": 0.057,
    "build_time_s": 14.31606125831604,
    "search_time_s": 0.018481969833374023,
    "bytes_per_vec": 12
  },
  {
    "method": "FAISS PQ m=8",
    "k": 64,
    "recall_1_at_k": 0.093,
    "build_time_s": 14.31606125831604,
    "search_time_s": 0.018481969833374023,
    "bytes_per_vec": 12
  }
]